{
  "items": [
    {
      "id": "PYROCLASTIC_SCALE",
      "name": "Pyroclastic Scale",
      "buy_price": 749.0,
      "sell_price": 3.4,
      "spread_pct": 21929.41,
      "est_buy_volume": 110820,
      "est_sell_volume": 602099,
      "buy_moving_week": 155148,
      "sell_moving_week": 842938
    },
    {
      "id": "WISHING_COMPASS",
      "name": "Wishing Compass",
      "buy_price": 8.88,
      "sell_price": 0.1,
      "spread_pct": 8781.36,
      "est_buy_volume": 296422,
      "est_sell_volume": 2725507,
      "buy_moving_week": 414991,
      "sell_moving_week": 3815710
    },
    {
      "id": "WOOL",
      "name": "Wool",
      "buy_price": 8.0,
      "sell_price": 0.1,
      "spread_pct": 7900.0,
      "est_buy_volume": 791386,
      "est_sell_volume": 3273965,
      "buy_moving_week": 1107941,
      "sell_moving_week": 4583551
    },
    {
      "id": "WILD_ROSE",
      "name": "Wild Rose",
      "buy_price": 5.0,
      "sell_price": 0.1,
      "spread_pct": 4895.97,
      "est_buy_volume": 8555796,
      "est_sell_volume": 78380130,
      "buy_moving_week": 11978115,
      "sell_moving_week": 109732182
    },
    {
      "id": "ENDER_STONE",
      "name": "Ender Stone",
      "buy_price": 4.42,
      "sell_price": 0.1,
      "spread_pct": 4317.26,
      "est_buy_volume": 1822583,
      "est_sell_volume": 21226328,
      "buy_moving_week": 2551616,
      "sell_moving_week": 29716859
    },
    {
      "id": "SHELLFRUIT",
      "name": "Shellfruit",
      "buy_price": 804.96,
      "sell_price": 24.02,
      "spread_pct": 3251.16,
      "est_buy_volume": 96356,
      "est_sell_volume": 151628,
      "buy_moving_week": 134899,
      "sell_moving_week": 212279
    },
    {
      "id": "SNOW_BALL",
      "name": "Snow Ball",
      "buy_price": 3.2,
      "sell_price": 0.1,
      "spread_pct": 3100.0,
      "est_buy_volume": 228229,
      "est_sell_volume": 1102847,
      "buy_moving_week": 319521,
      "sell_moving_week": 1543986
    },
    {
      "id": "GILL_MEMBRANE",
      "name": "Gill Membrane",
      "buy_price": 92.43,
      "sell_price": 3.2,
      "spread_pct": 2788.59,
      "est_buy_volume": 565489,
      "est_sell_volume": 1487096,
      "buy_moving_week": 791684,
      "sell_moving_week": 2081934
    },
    {
      "id": "RABBIT_FOOT",
      "name": "Rabbit Foot",
      "buy_price": 5.51,
      "sell_price": 0.2,
      "spread_pct": 2653.44,
      "est_buy_volume": 247100,
      "est_sell_volume": 1719130,
      "buy_moving_week": 345940,
      "sell_moving_week": 2406782
    },
    {
      "id": "EXPORTABLE_CARROTS",
      "name": "Exportable Carrots",
      "buy_price": 12216.23,
      "sell_price": 473.61,
      "spread_pct": 2479.4,
      "est_buy_volume": 219064,
      "est_sell_volume": 222649,
      "buy_moving_week": 306690,
      "sell_moving_week": 311709
    },
    {
      "id": "MINNOW_BAIT",
      "name": "Minnow Bait",
      "buy_price": 117.7,
      "sell_price": 5.1,
      "spread_pct": 2205.99,
      "est_buy_volume": 347216,
      "est_sell_volume": 487448,
      "buy_moving_week": 486103,
      "sell_moving_week": 682427
    },
    {
      "id": "ROUGH_CITRINE_GEM",
      "name": "Rough Citrine Gem",
      "buy_price": 17.52,
      "sell_price": 0.85,
      "spread_pct": 1964.05,
      "est_buy_volume": 264064,
      "est_sell_volume": 131203362,
      "buy_moving_week": 369690,
      "sell_moving_week": 183684707
    },
    {
      "id": "CORRUPTED_BAIT",
      "name": "Corrupted Bait",
      "buy_price": 282.7,
      "sell_price": 15.4,
      "spread_pct": 1735.73,
      "est_buy_volume": 337534,
      "est_sell_volume": 229391,
      "buy_moving_week": 472547,
      "sell_moving_week": 321147
    },
    {
      "id": "SAND:1",
      "name": "Sand:1",
      "buy_price": 31.55,
      "sell_price": 1.8,
      "spread_pct": 1652.68,
      "est_buy_volume": 795864,
      "est_sell_volume": 17467259,
      "buy_moving_week": 1114210,
      "sell_moving_week": 24454162
    },
    {
      "id": "LUMP_OF_MAGMA",
      "name": "Lump Of Magma",
      "buy_price": 54.9,
      "sell_price": 3.2,
      "spread_pct": 1615.58,
      "est_buy_volume": 223344,
      "est_sell_volume": 3131590,
      "buy_moving_week": 312682,
      "sell_moving_week": 4384226
    },
    {
      "id": "RABBIT_HIDE",
      "name": "Rabbit Hide",
      "buy_price": 28.9,
      "sell_price": 1.69,
      "spread_pct": 1614.74,
      "est_buy_volume": 600761,
      "est_sell_volume": 1790243,
      "buy_moving_week": 841066,
      "sell_moving_week": 2506340
    },
    {
      "id": "MELON",
      "name": "Melon",
      "buy_price": 8.46,
      "sell_price": 0.57,
      "spread_pct": 1384.04,
      "est_buy_volume": 19371294,
      "est_sell_volume": 416396303,
      "buy_moving_week": 27119811,
      "sell_moving_week": 582954824
    },
    {
      "id": "PRISMARINE_SHARD",
      "name": "Prismarine Shard",
      "buy_price": 3.17,
      "sell_price": 0.22,
      "spread_pct": 1334.13,
      "est_buy_volume": 435271,
      "est_sell_volume": 8098219,
      "buy_moving_week": 609380,
      "sell_moving_week": 11337507
    },
    {
      "id": "MOOGMA_PELT",
      "name": "Moogma Pelt",
      "buy_price": 54.12,
      "sell_price": 3.8,
      "spread_pct": 1324.21,
      "est_buy_volume": 366121,
      "est_sell_volume": 2285852,
      "buy_moving_week": 512570,
      "sell_moving_week": 3200193
    },
    {
      "id": "CHUM",
      "name": "Chum",
      "buy_price": 4.0,
      "sell_price": 0.3,
      "spread_pct": 1233.33,
      "est_buy_volume": 2045841,
      "est_sell_volume": 6380324,
      "buy_moving_week": 2864177,
      "sell_moving_week": 8932453
    },
    {
      "id": "QUARTZ",
      "name": "Quartz",
      "buy_price": 55.53,
      "sell_price": 4.21,
      "spread_pct": 1219.64,
      "est_buy_volume": 3172330,
      "est_sell_volume": 25053228,
      "buy_moving_week": 4441262,
      "sell_moving_week": 35074519
    },
    {
      "id": "CLAY_BALL",
      "name": "Clay Ball",
      "buy_price": 16.7,
      "sell_price": 1.3,
      "spread_pct": 1184.62,
      "est_buy_volume": 2077413,
      "est_sell_volume": 13668808,
      "buy_moving_week": 2908378,
      "sell_moving_week": 19136331
    },
    {
      "id": "DOUBLE_PLANT",
      "name": "Double Plant",
      "buy_price": 5.0,
      "sell_price": 0.4,
      "spread_pct": 1148.82,
      "est_buy_volume": 14591291,
      "est_sell_volume": 134659514,
      "buy_moving_week": 20427808,
      "sell_moving_week": 188523319
    },
    {
      "id": "ENCHANTED_WOOL",
      "name": "Enchanted Wool",
      "buy_price": 311.41,
      "sell_price": 25.3,
      "spread_pct": 1130.85,
      "est_buy_volume": 468555,
      "est_sell_volume": 6828719,
      "buy_moving_week": 655977,
      "sell_moving_week": 9560206
    },
    {
      "id": "GLOWSTONE_DUST",
      "name": "Glowstone Dust",
      "buy_price": 28.61,
      "sell_price": 2.7,
      "spread_pct": 959.71,
      "est_buy_volume": 922272,
      "est_sell_volume": 7997889,
      "buy_moving_week": 1291181,
      "sell_moving_week": 11197044
    },
    {
      "id": "ROUGH_AQUAMARINE_GEM",
      "name": "Rough Aquamarine Gem",
      "buy_price": 7.02,
      "sell_price": 0.7,
      "spread_pct": 902.65,
      "est_buy_volume": 413758,
      "est_sell_volume": 151174859,
      "buy_moving_week": 579261,
      "sell_moving_week": 211644803
    },
    {
      "id": "ICE_BAIT",
      "name": "Ice Bait",
      "buy_price": 1.0,
      "sell_price": 0.1,
      "spread_pct": 898.44,
      "est_buy_volume": 565641,
      "est_sell_volume": 791686,
      "buy_moving_week": 791898,
      "sell_moving_week": 1108360
    },
    {
      "id": "MYCEL",
      "name": "Mycel",
      "buy_price": 26.81,
      "sell_price": 2.8,
      "spread_pct": 857.04,
      "est_buy_volume": 5610043,
      "est_sell_volume": 21711029,
      "buy_moving_week": 7854060,
      "sell_moving_week": 30395441
    },
    {
      "id": "SUPREME_CHOCOLATE_BAR",
      "name": "Supreme Chocolate Bar",
      "buy_price": 286.32,
      "sell_price": 30.7,
      "spread_pct": 832.65,
      "est_buy_volume": 487530,
      "est_sell_volume": 297556,
      "buy_moving_week": 682542,
      "sell_moving_week": 416579
    },
    {
      "id": "SAND",
      "name": "Sand",
      "buy_price": 18.48,
      "sell_price": 2.0,
      "spread_pct": 824.07,
      "est_buy_volume": 5838301,
      "est_sell_volume": 7507794,
      "buy_moving_week": 8173622,
      "sell_moving_week": 10510911
    },
    {
      "id": "STURDY_BONE",
      "name": "Sturdy Bone",
      "buy_price": 788.7,
      "sell_price": 86.9,
      "spread_pct": 807.59,
      "est_buy_volume": 135269,
      "est_sell_volume": 426283,
      "buy_moving_week": 189377,
      "sell_moving_week": 596796
    },
    {
      "id": "GHAST_TEAR",
      "name": "Ghast Tear",
      "buy_price": 486.7,
      "sell_price": 54.46,
      "spread_pct": 793.63,
      "est_buy_volume": 505046,
      "est_sell_volume": 660825,
      "buy_moving_week": 707064,
      "sell_moving_week": 925155
    },
    {
      "id": "SPONGE",
      "name": "Sponge",
      "buy_price": 254.94,
      "sell_price": 28.94,
      "spread_pct": 780.81,
      "est_buy_volume": 321640,
      "est_sell_volume": 4307508,
      "buy_moving_week": 450296,
      "sell_moving_week": 6030511
    },
    {
      "id": "ROUGH_RUBY_GEM",
      "name": "Rough Ruby Gem",
      "buy_price": 6.35,
      "sell_price": 0.74,
      "spread_pct": 754.51,
      "est_buy_volume": 1175233,
      "est_sell_volume": 128329516,
      "buy_moving_week": 1645326,
      "sell_moving_week": 179661323
    },
    {
      "id": "YOGGIE",
      "name": "Yoggie",
      "buy_price": 123.95,
      "sell_price": 15.2,
      "spread_pct": 715.45,
      "est_buy_volume": 174285,
      "est_sell_volume": 511282,
      "buy_moving_week": 243999,
      "sell_moving_week": 715795
    },
    {
      "id": "RAW_FISH:1",
      "name": "Raw Fish:1",
      "buy_price": 52.8,
      "sell_price": 6.67,
      "spread_pct": 691.13,
      "est_buy_volume": 1227941,
      "est_sell_volume": 21631466,
      "buy_moving_week": 1719117,
      "sell_moving_week": 30284052
    },
    {
      "id": "ASCENSION_ROPE",
      "name": "Ascension Rope",
      "buy_price": 382.99,
      "sell_price": 51.3,
      "spread_pct": 646.57,
      "est_buy_volume": 233445,
      "est_sell_volume": 459217,
      "buy_moving_week": 326823,
      "sell_moving_week": 642904
    },
    {
      "id": "LOG_2",
      "name": "Log 2",
      "buy_price": 19.0,
      "sell_price": 2.75,
      "spread_pct": 590.39,
      "est_buy_volume": 1063757,
      "est_sell_volume": 8606459,
      "buy_moving_week": 1489260,
      "sell_moving_week": 12049043
    },
    {
      "id": "HOT_BAIT",
      "name": "Hot Bait",
      "buy_price": 198.54,
      "sell_price": 28.85,
      "spread_pct": 588.24,
      "est_buy_volume": 4477546,
      "est_sell_volume": 3002969,
      "buy_moving_week": 6268565,
      "sell_moving_week": 4204157
    },
    {
      "id": "SULPHUR",
      "name": "Sulphur",
      "buy_price": 36.9,
      "sell_price": 5.71,
      "spread_pct": 546.11,
      "est_buy_volume": 1528916,
      "est_sell_volume": 2851074,
      "buy_moving_week": 2140482,
      "sell_moving_week": 3991503
    },
    {
      "id": "POISONOUS_POTATO",
      "name": "Poisonous Potato",
      "buy_price": 20.0,
      "sell_price": 3.1,
      "spread_pct": 545.15,
      "est_buy_volume": 91224,
      "est_sell_volume": 555121,
      "buy_moving_week": 127714,
      "sell_moving_week": 777169
    },
    {
      "id": "MELON_BLOCK",
      "name": "Melon Block",
      "buy_price": 243.94,
      "sell_price": 37.86,
      "spread_pct": 544.25,
      "est_buy_volume": 1846743,
      "est_sell_volume": 1208309,
      "buy_moving_week": 2585440,
      "sell_moving_week": 1691632
    },
    {
      "id": "GOLD_INGOT",
      "name": "Gold Ingot",
      "buy_price": 7.08,
      "sell_price": 1.1,
      "spread_pct": 543.88,
      "est_buy_volume": 9860434,
      "est_sell_volume": 195618729,
      "buy_moving_week": 13804607,
      "sell_moving_week": 273866221
    },
    {
      "id": "MAGMA_CREAM",
      "name": "Magma Cream",
      "buy_price": 19.05,
      "sell_price": 3.01,
      "spread_pct": 531.89,
      "est_buy_volume": 1301020,
      "est_sell_volume": 7817306,
      "buy_moving_week": 1821428,
      "sell_moving_week": 10944229
    },
    {
      "id": "MANGROVE_LOG",
      "name": "Mangrove Log",
      "buy_price": 44.69,
      "sell_price": 7.26,
      "spread_pct": 515.45,
      "est_buy_volume": 1342444,
      "est_sell_volume": 165723001,
      "buy_moving_week": 1879422,
      "sell_moving_week": 232012202
    },
    {
      "id": "RAW_CHICKEN",
      "name": "Raw Chicken",
      "buy_price": 93.19,
      "sell_price": 15.4,
      "spread_pct": 505.15,
      "est_buy_volume": 2094546,
      "est_sell_volume": 3186973,
      "buy_moving_week": 2932365,
      "sell_moving_week": 4461762
    },
    {
      "id": "PORK",
      "name": "Pork",
      "buy_price": 66.92,
      "sell_price": 11.27,
      "spread_pct": 493.56,
      "est_buy_volume": 1177469,
      "est_sell_volume": 2377964,
      "buy_moving_week": 1648457,
      "sell_moving_week": 3329150
    },
    {
      "id": "ROTTEN_FLESH",
      "name": "Rotten Flesh",
      "buy_price": 4.72,
      "sell_price": 0.8,
      "spread_pct": 490.31,
      "est_buy_volume": 3595969,
      "est_sell_volume": 31573756,
      "buy_moving_week": 5034356,
      "sell_moving_week": 44203259
    },
    {
      "id": "MUTTON",
      "name": "Mutton",
      "buy_price": 60.85,
      "sell_price": 10.31,
      "spread_pct": 489.91,
      "est_buy_volume": 2245009,
      "est_sell_volume": 3407154,
      "buy_moving_week": 3143012,
      "sell_moving_week": 4770016
    },
    {
      "id": "RAW_BEEF",
      "name": "Raw Beef",
      "buy_price": 11.43,
      "sell_price": 2.01,
      "spread_pct": 469.13,
      "est_buy_volume": 1825969,
      "est_sell_volume": 5220339,
      "buy_moving_week": 2556357,
      "sell_moving_week": 7308474
    },
    {
      "id": "MOONFLOWER",
      "name": "Moonflower",
      "buy_price": 5.58,
      "sell_price": 1.07,
      "spread_pct": 422.73,
      "est_buy_volume": 3860824,
      "est_sell_volume": 109322464,
      "buy_moving_week": 5405154,
      "sell_moving_week": 153051449
    },
    {
      "id": "INK_SACK:3",
      "name": "Ink Sack:3",
      "buy_price": 13.89,
      "sell_price": 2.7,
      "spread_pct": 414.33,
      "est_buy_volume": 20449960,
      "est_sell_volume": 66044984,
      "buy_moving_week": 28629944,
      "sell_moving_week": 92462977
    },
    {
      "id": "SPIDER_EYE",
      "name": "Spider Eye",
      "buy_price": 6.67,
      "sell_price": 1.3,
      "spread_pct": 412.88,
      "est_buy_volume": 944012,
      "est_sell_volume": 19990464,
      "buy_moving_week": 1321617,
      "sell_moving_week": 27986649
    },
    {
      "id": "SPIRIT_LEAP",
      "name": "Spirit Leap",
      "buy_price": 387.6,
      "sell_price": 76.13,
      "spread_pct": 409.14,
      "est_buy_volume": 322468,
      "est_sell_volume": 985816,
      "buy_moving_week": 451455,
      "sell_moving_week": 1380142
    },
    {
      "id": "CARROT_BAIT",
      "name": "Carrot Bait",
      "buy_price": 381.03,
      "sell_price": 75.0,
      "spread_pct": 408.05,
      "est_buy_volume": 286511,
      "est_sell_volume": 240770,
      "buy_moving_week": 401116,
      "sell_moving_week": 337078
    },
    {
      "id": "SEEDS",
      "name": "Seeds",
      "buy_price": 4.25,
      "sell_price": 0.84,
      "spread_pct": 406.79,
      "est_buy_volume": 48850571,
      "est_sell_volume": 822200634,
      "buy_moving_week": 68390800,
      "sell_moving_week": 1151080887
    },
    {
      "id": "RABBIT",
      "name": "Rabbit",
      "buy_price": 108.31,
      "sell_price": 21.5,
      "spread_pct": 403.75,
      "est_buy_volume": 2069467,
      "est_sell_volume": 2835209,
      "buy_moving_week": 2897254,
      "sell_moving_week": 3969293
    },
    {
      "id": "SUPERBOOM_TNT",
      "name": "Superboom Tnt",
      "buy_price": 99.69,
      "sell_price": 20.43,
      "spread_pct": 387.98,
      "est_buy_volume": 1594209,
      "est_sell_volume": 2234334,
      "buy_moving_week": 2231893,
      "sell_moving_week": 3128067
    },
    {
      "id": "BONE",
      "name": "Bone",
      "buy_price": 4.86,
      "sell_price": 1.0,
      "spread_pct": 385.94,
      "est_buy_volume": 1664918,
      "est_sell_volume": 12790671,
      "buy_moving_week": 2330885,
      "sell_moving_week": 17906939
    },
    {
      "id": "BLAZE_ASHES",
      "name": "Blaze Ashes",
      "buy_price": 49.2,
      "sell_price": 10.5,
      "spread_pct": 368.57,
      "est_buy_volume": 444114,
      "est_sell_volume": 1863208,
      "buy_moving_week": 621760,
      "sell_moving_week": 2608491
    },
    {
      "id": "EXP_BOTTLE",
      "name": "Exp Bottle",
      "buy_price": 52.26,
      "sell_price": 11.4,
      "spread_pct": 358.46,
      "est_buy_volume": 285852,
      "est_sell_volume": 348448,
      "buy_moving_week": 400193,
      "sell_moving_week": 487827
    },
    {
      "id": "ENCHANTED_PAPER",
      "name": "Enchanted Paper",
      "buy_price": 2233.08,
      "sell_price": 488.4,
      "spread_pct": 357.22,
      "est_buy_volume": 308349,
      "est_sell_volume": 171004,
      "buy_moving_week": 431689,
      "sell_moving_week": 239406
    },
    {
      "id": "ROUGH_JASPER_GEM",
      "name": "Rough Jasper Gem",
      "buy_price": 39.83,
      "sell_price": 8.79,
      "spread_pct": 353.02,
      "est_buy_volume": 146956,
      "est_sell_volume": 76911719,
      "buy_moving_week": 205739,
      "sell_moving_week": 107676407
    },
    {
      "id": "SPOOKY_BAIT",
      "name": "Spooky Bait",
      "buy_price": 454.87,
      "sell_price": 102.31,
      "spread_pct": 344.61,
      "est_buy_volume": 1130222,
      "est_sell_volume": 526664,
      "buy_moving_week": 1582311,
      "sell_moving_week": 737330
    },
    {
      "id": "LUSHLILAC",
      "name": "Lushlilac",
      "buy_price": 1.7,
      "sell_price": 0.4,
      "spread_pct": 325.18,
      "est_buy_volume": 766926,
      "est_sell_volume": 6408194,
      "buy_moving_week": 1073697,
      "sell_moving_week": 8971471
    },
    {
      "id": "STRING",
      "name": "String",
      "buy_price": 14.44,
      "sell_price": 3.4,
      "spread_pct": 324.67,
      "est_buy_volume": 2646776,
      "est_sell_volume": 36999818,
      "buy_moving_week": 3705486,
      "sell_moving_week": 51799745
    },
    {
      "id": "LOG_2:1",
      "name": "Log 2:1",
      "buy_price": 38.85,
      "sell_price": 9.16,
      "spread_pct": 324.09,
      "est_buy_volume": 1819926,
      "est_sell_volume": 9906391,
      "buy_moving_week": 2547897,
      "sell_moving_week": 13868948
    },
    {
      "id": "ROUGH_PERIDOT_GEM",
      "name": "Rough Peridot Gem",
      "buy_price": 9.49,
      "sell_price": 2.25,
      "spread_pct": 322.27,
      "est_buy_volume": 558995,
      "est_sell_volume": 174460463,
      "buy_moving_week": 782593,
      "sell_moving_week": 244244648
    },
    {
      "id": "ENDER_PEARL",
      "name": "Ender Pearl",
      "buy_price": 12.71,
      "sell_price": 3.1,
      "spread_pct": 310.15,
      "est_buy_volume": 2593876,
      "est_sell_volume": 83762733,
      "buy_moving_week": 3631427,
      "sell_moving_week": 117267826
    },
    {
      "id": "ROUGH_ONYX_GEM",
      "name": "Rough Onyx Gem",
      "buy_price": 4.63,
      "sell_price": 1.2,
      "spread_pct": 285.45,
      "est_buy_volume": 156603,
      "est_sell_volume": 127568600,
      "buy_moving_week": 219244,
      "sell_moving_week": 178596040
    },
    {
      "id": "COBBLESTONE",
      "name": "Cobblestone",
      "buy_price": 4.2,
      "sell_price": 1.1,
      "spread_pct": 281.77,
      "est_buy_volume": 5863635,
      "est_sell_volume": 79482821,
      "buy_moving_week": 8209089,
      "sell_moving_week": 111275950
    },
    {
      "id": "LOG:3",
      "name": "Log:3",
      "buy_price": 43.45,
      "sell_price": 11.47,
      "spread_pct": 278.86,
      "est_buy_volume": 5038987,
      "est_sell_volume": 12485489,
      "buy_moving_week": 7054582,
      "sell_moving_week": 17479684
    },
    {
      "id": "LOG",
      "name": "Log",
      "buy_price": 14.06,
      "sell_price": 3.74,
      "spread_pct": 276.36,
      "est_buy_volume": 2968571,
      "est_sell_volume": 14896778,
      "buy_moving_week": 4156000,
      "sell_moving_week": 20855489
    },
    {
      "id": "TENTACLE_MEAT",
      "name": "Tentacle Meat",
      "buy_price": 4973.34,
      "sell_price": 1387.9,
      "spread_pct": 258.34,
      "est_buy_volume": 91520,
      "est_sell_volume": 91786,
      "buy_moving_week": 128128,
      "sell_moving_week": 128501
    },
    {
      "id": "ROUGH_TOPAZ_GEM",
      "name": "Rough Topaz Gem",
      "buy_price": 4.65,
      "sell_price": 1.31,
      "spread_pct": 253.45,
      "est_buy_volume": 641616,
      "est_sell_volume": 197450029,
      "buy_moving_week": 898262,
      "sell_moving_week": 276430040
    },
    {
      "id": "RAW_FISH:2",
      "name": "Raw Fish:2",
      "buy_price": 18.26,
      "sell_price": 5.2,
      "spread_pct": 251.09,
      "est_buy_volume": 181034,
      "est_sell_volume": 12846181,
      "buy_moving_week": 253448,
      "sell_moving_week": 17984653
    },
    {
      "id": "PUMPKIN",
      "name": "Pumpkin",
      "buy_price": 31.0,
      "sell_price": 8.88,
      "spread_pct": 249.17,
      "est_buy_volume": 7638153,
      "est_sell_volume": 105776283,
      "buy_moving_week": 10693414,
      "sell_moving_week": 148086796
    },
    {
      "id": "POTATO_ITEM",
      "name": "Potato Item",
      "buy_price": 10.47,
      "sell_price": 3.0,
      "spread_pct": 249.02,
      "est_buy_volume": 19238443,
      "est_sell_volume": 105144796,
      "buy_moving_week": 26933820,
      "sell_moving_week": 147202714
    },
    {
      "id": "LOG:1",
      "name": "Log:1",
      "buy_price": 5.75,
      "sell_price": 1.7,
      "spread_pct": 238.45,
      "est_buy_volume": 2678200,
      "est_sell_volume": 6910980,
      "buy_moving_week": 3749480,
      "sell_moving_week": 9675372
    },
    {
      "id": "HEMOVIBE",
      "name": "Hemovibe",
      "buy_price": 295.3,
      "sell_price": 89.68,
      "spread_pct": 229.27,
      "est_buy_volume": 335564,
      "est_sell_volume": 595841,
      "buy_moving_week": 469789,
      "sell_moving_week": 834178
    },
    {
      "id": "RED_ROSE",
      "name": "Red Rose",
      "buy_price": 98.47,
      "sell_price": 30.5,
      "spread_pct": 222.86,
      "est_buy_volume": 241611,
      "est_sell_volume": 506528,
      "buy_moving_week": 338255,
      "sell_moving_week": 709139
    },
    {
      "id": "CARROT_ITEM",
      "name": "Carrot Item",
      "buy_price": 6.94,
      "sell_price": 2.21,
      "spread_pct": 213.87,
      "est_buy_volume": 23893527,
      "est_sell_volume": 137599201,
      "buy_moving_week": 33450938,
      "sell_moving_week": 192638882
    },
    {
      "id": "ROUGH_JADE_GEM",
      "name": "Rough Jade Gem",
      "buy_price": 5.11,
      "sell_price": 1.64,
      "spread_pct": 212.71,
      "est_buy_volume": 1064495,
      "est_sell_volume": 232934149,
      "buy_moving_week": 1490293,
      "sell_moving_week": 326107808
    },
    {
      "id": "FLINT",
      "name": "Flint",
      "buy_price": 25.95,
      "sell_price": 8.3,
      "spread_pct": 212.59,
      "est_buy_volume": 433235,
      "est_sell_volume": 29298339,
      "buy_moving_week": 606529,
      "sell_moving_week": 41017674
    },
    {
      "id": "ROUGH_AMBER_GEM",
      "name": "Rough Amber Gem",
      "buy_price": 4.28,
      "sell_price": 1.42,
      "spread_pct": 201.95,
      "est_buy_volume": 447959,
      "est_sell_volume": 195366785,
      "buy_moving_week": 627143,
      "sell_moving_week": 273513499
    },
    {
      "id": "ENCHANTED_NETHERRACK",
      "name": "Enchanted Netherrack",
      "buy_price": 299.99,
      "sell_price": 100.01,
      "spread_pct": 199.95,
      "est_buy_volume": 102111,
      "est_sell_volume": 686816,
      "buy_moving_week": 142955,
      "sell_moving_week": 961543
    },
    {
      "id": "ROUGH_SAPPHIRE_GEM",
      "name": "Rough Sapphire Gem",
      "buy_price": 3.8,
      "sell_price": 1.3,
      "spread_pct": 192.12,
      "est_buy_volume": 996143,
      "est_sell_volume": 388420599,
      "buy_moving_week": 1394600,
      "sell_moving_week": 543788838
    },
    {
      "id": "GLACITE",
      "name": "Glacite",
      "buy_price": 11.48,
      "sell_price": 4.01,
      "spread_pct": 186.16,
      "est_buy_volume": 3154120,
      "est_sell_volume": 409746451,
      "buy_moving_week": 4415768,
      "sell_moving_week": 573645032
    },
    {
      "id": "CACTUS",
      "name": "Cactus",
      "buy_price": 6.04,
      "sell_price": 2.2,
      "spread_pct": 174.55,
      "est_buy_volume": 6741374,
      "est_sell_volume": 33904293,
      "buy_moving_week": 9437923,
      "sell_moving_week": 47466010
    },
    {
      "id": "DIGESTED_MUSHROOMS",
      "name": "Digested Mushrooms",
      "buy_price": 12018.88,
      "sell_price": 4403.2,
      "spread_pct": 172.96,
      "est_buy_volume": 106256,
      "est_sell_volume": 118756,
      "buy_moving_week": 148758,
      "sell_moving_week": 166259
    },
    {
      "id": "PACKED_ICE",
      "name": "Packed Ice",
      "buy_price": 176.96,
      "sell_price": 64.93,
      "spread_pct": 172.54,
      "est_buy_volume": 2812466,
      "est_sell_volume": 2546531,
      "buy_moving_week": 3937453,
      "sell_moving_week": 3565144
    },
    {
      "id": "SUGAR_CANE",
      "name": "Sugar Cane",
      "buy_price": 8.34,
      "sell_price": 3.08,
      "spread_pct": 171.0,
      "est_buy_volume": 15820131,
      "est_sell_volume": 118873139,
      "buy_moving_week": 22148183,
      "sell_moving_week": 166422394
    },
    {
      "id": "EMERALD",
      "name": "Emerald",
      "buy_price": 8.36,
      "sell_price": 3.1,
      "spread_pct": 169.64,
      "est_buy_volume": 6473609,
      "est_sell_volume": 66091261,
      "buy_moving_week": 9063052,
      "sell_moving_week": 92527765
    },
    {
      "id": "WATER_LILY",
      "name": "Water Lily",
      "buy_price": 86.43,
      "sell_price": 32.4,
      "spread_pct": 166.75,
      "est_buy_volume": 6644603,
      "est_sell_volume": 31665347,
      "buy_moving_week": 9302444,
      "sell_moving_week": 44331486
    },
    {
      "id": "CHOCONUT",
      "name": "Choconut",
      "buy_price": 2131.09,
      "sell_price": 814.32,
      "spread_pct": 161.7,
      "est_buy_volume": 153091,
      "est_sell_volume": 113330,
      "buy_moving_week": 214327,
      "sell_moving_week": 158662
    },
    {
      "id": "ANCIENT_CLAW",
      "name": "Ancient Claw",
      "buy_price": 493.98,
      "sell_price": 189.95,
      "spread_pct": 160.06,
      "est_buy_volume": 301631,
      "est_sell_volume": 2404640,
      "buy_moving_week": 422284,
      "sell_moving_week": 3366496
    },
    {
      "id": "ENCHANTED_SPRUCE_LOG",
      "name": "Enchanted Spruce Log",
      "buy_price": 2488.28,
      "sell_price": 958.82,
      "spread_pct": 159.52,
      "est_buy_volume": 678715,
      "est_sell_volume": 1104201,
      "buy_moving_week": 950201,
      "sell_moving_week": 1545881
    },
    {
      "id": "RAW_SOULFLOW",
      "name": "Raw Soulflow",
      "buy_price": 802.22,
      "sell_price": 309.16,
      "spread_pct": 159.48,
      "est_buy_volume": 833459,
      "est_sell_volume": 1031749,
      "buy_moving_week": 1166843,
      "sell_moving_week": 1444449
    },
    {
      "id": "SULPHUR_ORE",
      "name": "Sulphur Ore",
      "buy_price": 17.0,
      "sell_price": 6.6,
      "spread_pct": 157.58,
      "est_buy_volume": 259921,
      "est_sell_volume": 9825468,
      "buy_moving_week": 363890,
      "sell_moving_week": 13755655
    },
    {
      "id": "BLAZE_ROD",
      "name": "Blaze Rod",
      "buy_price": 40.0,
      "sell_price": 15.8,
      "spread_pct": 153.16,
      "est_buy_volume": 2171177,
      "est_sell_volume": 29501404,
      "buy_moving_week": 3039648,
      "sell_moving_week": 41301966
    },
    {
      "id": "ROUGH_AMETHYST_GEM",
      "name": "Rough Amethyst Gem",
      "buy_price": 4.14,
      "sell_price": 1.67,
      "spread_pct": 148.73,
      "est_buy_volume": 563296,
      "est_sell_volume": 259603074,
      "buy_moving_week": 788615,
      "sell_moving_week": 363444303
    },
    {
      "id": "WHEAT",
      "name": "Wheat",
      "buy_price": 5.61,
      "sell_price": 2.36,
      "spread_pct": 138.04,
      "est_buy_volume": 11022770,
      "est_sell_volume": 779960484,
      "buy_moving_week": 15431878,
      "sell_moving_week": 1091944677
    },
    {
      "id": "ASHWREATH",
      "name": "Ashwreath",
      "buy_price": 1360.12,
      "sell_price": 581.75,
      "spread_pct": 133.8,
      "est_buy_volume": 567005,
      "est_sell_volume": 2232019,
      "buy_moving_week": 793807,
      "sell_moving_week": 3124826
    },
    {
      "id": "BROWN_MUSHROOM",
      "name": "Brown Mushroom",
      "buy_price": 17.05,
      "sell_price": 7.3,
      "spread_pct": 133.54,
      "est_buy_volume": 2033434,
      "est_sell_volume": 270622815,
      "buy_moving_week": 2846807,
      "sell_moving_week": 378871941
    },
    {
      "id": "HONEY_JAR",
      "name": "Honey Jar",
      "buy_price": 1411.96,
      "sell_price": 606.72,
      "spread_pct": 132.72,
      "est_buy_volume": 279452,
      "est_sell_volume": 576713,
      "buy_moving_week": 391233,
      "sell_moving_week": 807398
    },
    {
      "id": "LEATHER",
      "name": "Leather",
      "buy_price": 177.47,
      "sell_price": 78.39,
      "spread_pct": 126.41,
      "est_buy_volume": 4083334,
      "est_sell_volume": 8519694,
      "buy_moving_week": 5716667,
      "sell_moving_week": 11927571
    },
    {
      "id": "RAW_FISH:3",
      "name": "Raw Fish:3",
      "buy_price": 14.9,
      "sell_price": 6.6,
      "spread_pct": 125.76,
      "est_buy_volume": 345121,
      "est_sell_volume": 16122036,
      "buy_moving_week": 483169,
      "sell_moving_week": 22570851
    },
    {
      "id": "MAGMA_CHUNK",
      "name": "Magma Chunk",
      "buy_price": 846.54,
      "sell_price": 375.78,
      "spread_pct": 125.27,
      "est_buy_volume": 247179,
      "est_sell_volume": 814636,
      "buy_moving_week": 346050,
      "sell_moving_week": 1140490
    },
    {
      "id": "ENCHANTED_MYCELIUM",
      "name": "Enchanted Mycelium",
      "buy_price": 1526.68,
      "sell_price": 684.08,
      "spread_pct": 123.17,
      "est_buy_volume": 4777171,
      "est_sell_volume": 6889079,
      "buy_moving_week": 6688039,
      "sell_moving_week": 9644711
    },
    {
      "id": "OBSIDIAN",
      "name": "Obsidian",
      "buy_price": 30.88,
      "sell_price": 14.26,
      "spread_pct": 116.62,
      "est_buy_volume": 2492584,
      "est_sell_volume": 37558236,
      "buy_moving_week": 3489617,
      "sell_moving_week": 52581530
    },
    {
      "id": "GLOOMGOURD",
      "name": "Gloomgourd",
      "buy_price": 1400.0,
      "sell_price": 672.02,
      "spread_pct": 108.33,
      "est_buy_volume": 214883,
      "est_sell_volume": 263656,
      "buy_moving_week": 300836,
      "sell_moving_week": 369119
    },
    {
      "id": "MITHRIL_ORE",
      "name": "Mithril Ore",
      "buy_price": 13.37,
      "sell_price": 6.44,
      "spread_pct": 107.76,
      "est_buy_volume": 5102553,
      "est_sell_volume": 699035444,
      "buy_moving_week": 7143574,
      "sell_moving_week": 978649622
    },
    {
      "id": "LOTUS",
      "name": "Lotus",
      "buy_price": 344.95,
      "sell_price": 166.29,
      "spread_pct": 107.45,
      "est_buy_volume": 159534,
      "est_sell_volume": 12812241,
      "buy_moving_week": 223347,
      "sell_moving_week": 17937138
    },
    {
      "id": "DEAD_PLANT",
      "name": "Dead Plant",
      "buy_price": 1110.63,
      "sell_price": 555.41,
      "spread_pct": 99.97,
      "est_buy_volume": 196923,
      "est_sell_volume": 525875,
      "buy_moving_week": 275692,
      "sell_moving_week": 736225
    },
    {
      "id": "SEA_LUMIES",
      "name": "Sea Lumies",
      "buy_price": 697.71,
      "sell_price": 351.74,
      "spread_pct": 98.36,
      "est_buy_volume": 284324,
      "est_sell_volume": 5952668,
      "buy_moving_week": 398054,
      "sell_moving_week": 8333735
    },
    {
      "id": "ENCHANTED_BIRCH_LOG",
      "name": "Enchanted Birch Log",
      "buy_price": 588.94,
      "sell_price": 298.9,
      "spread_pct": 97.04,
      "est_buy_volume": 978131,
      "est_sell_volume": 1296705,
      "buy_moving_week": 1369384,
      "sell_moving_week": 1815387
    },
    {
      "id": "BLESSED_BAIT",
      "name": "Blessed Bait",
      "buy_price": 2596.66,
      "sell_price": 1319.41,
      "spread_pct": 96.81,
      "est_buy_volume": 281652,
      "est_sell_volume": 152803,
      "buy_moving_week": 394313,
      "sell_moving_week": 213924
    },
    {
      "id": "ENCHANTED_LUSH_BERBERIS",
      "name": "Enchanted Lush Berberis",
      "buy_price": 4491.9,
      "sell_price": 2297.82,
      "spread_pct": 95.49,
      "est_buy_volume": 495114,
      "est_sell_volume": 729907,
      "buy_moving_week": 693159,
      "sell_moving_week": 1021870
    },
    {
      "id": "DUNG",
      "name": "Dung",
      "buy_price": 1228.94,
      "sell_price": 636.21,
      "spread_pct": 93.17,
      "est_buy_volume": 391329,
      "est_sell_volume": 638496,
      "buy_moving_week": 547860,
      "sell_moving_week": 893894
    },
    {
      "id": "UMBER",
      "name": "Umber",
      "buy_price": 154.54,
      "sell_price": 80.69,
      "spread_pct": 91.53,
      "est_buy_volume": 156050,
      "est_sell_volume": 129928084,
      "buy_moving_week": 218470,
      "sell_moving_week": 181899317
    },
    {
      "id": "CAN_OF_WORMS",
      "name": "Can Of Worms",
      "buy_price": 18993.53,
      "sell_price": 10001.0,
      "spread_pct": 89.92,
      "est_buy_volume": 152217,
      "est_sell_volume": 161671,
      "buy_moving_week": 213104,
      "sell_moving_week": 226339
    },
    {
      "id": "DUNGEON_DECOY",
      "name": "Dungeon Decoy",
      "buy_price": 940.9,
      "sell_price": 500.0,
      "spread_pct": 88.18,
      "est_buy_volume": 127307,
      "est_sell_volume": 248866,
      "buy_moving_week": 178230,
      "sell_moving_week": 348412
    },
    {
      "id": "SPIKED_BAIT",
      "name": "Spiked Bait",
      "buy_price": 396.6,
      "sell_price": 212.93,
      "spread_pct": 86.26,
      "est_buy_volume": 1059774,
      "est_sell_volume": 890755,
      "buy_moving_week": 1483684,
      "sell_moving_week": 1247057
    },
    {
      "id": "ENCHANTED_SPONGE",
      "name": "Enchanted Sponge",
      "buy_price": 2294.75,
      "sell_price": 1234.57,
      "spread_pct": 85.87,
      "est_buy_volume": 98154,
      "est_sell_volume": 1184351,
      "buy_moving_week": 137415,
      "sell_moving_week": 1658092
    },
    {
      "id": "INK_SACK:4",
      "name": "Ink Sack:4",
      "buy_price": 6.1,
      "sell_price": 3.31,
      "spread_pct": 84.35,
      "est_buy_volume": 2835291,
      "est_sell_volume": 105840969,
      "buy_moving_week": 3969408,
      "sell_moving_week": 148177357
    },
    {
      "id": "COAL",
      "name": "Coal",
      "buy_price": 13.0,
      "sell_price": 7.06,
      "spread_pct": 84.24,
      "est_buy_volume": 33292446,
      "est_sell_volume": 654158579,
      "buy_moving_week": 46609425,
      "sell_moving_week": 915822011
    },
    {
      "id": "REDSTONE",
      "name": "Redstone",
      "buy_price": 8.81,
      "sell_price": 4.83,
      "spread_pct": 82.53,
      "est_buy_volume": 10506391,
      "est_sell_volume": 244006883,
      "buy_moving_week": 14708947,
      "sell_moving_week": 341609636
    },
    {
      "id": "ENCHANTED_JUNGLE_LOG",
      "name": "Enchanted Jungle Log",
      "buy_price": 3550.18,
      "sell_price": 2018.51,
      "spread_pct": 75.88,
      "est_buy_volume": 1739685,
      "est_sell_volume": 1902146,
      "buy_moving_week": 2435559,
      "sell_moving_week": 2663004
    },
    {
      "id": "SHARD_BIRRIES",
      "name": "Shard Birries",
      "buy_price": 3994.83,
      "sell_price": 2287.08,
      "spread_pct": 74.67,
      "est_buy_volume": 114714,
      "est_sell_volume": 123927,
      "buy_moving_week": 160599,
      "sell_moving_week": 173498
    },
    {
      "id": "YELLOW_FLOWER",
      "name": "Yellow Flower",
      "buy_price": 130.28,
      "sell_price": 74.65,
      "spread_pct": 74.51,
      "est_buy_volume": 444329,
      "est_sell_volume": 448450,
      "buy_moving_week": 622060,
      "sell_moving_week": 627830
    },
    {
      "id": "RAW_FISH",
      "name": "Raw Fish",
      "buy_price": 144.33,
      "sell_price": 83.5,
      "spread_pct": 72.85,
      "est_buy_volume": 7260516,
      "est_sell_volume": 34155311,
      "buy_moving_week": 10164723,
      "sell_moving_week": 47817436
    },
    {
      "id": "TWILIGHT_ARROW_POISON",
      "name": "Twilight Arrow Poison",
      "buy_price": 1265.78,
      "sell_price": 733.63,
      "spread_pct": 72.54,
      "est_buy_volume": 1277786,
      "est_sell_volume": 1412973,
      "buy_moving_week": 1788900,
      "sell_moving_week": 1978162
    },
    {
      "id": "SHARD_SEA_ARCHER",
      "name": "Shard Sea Archer",
      "buy_price": 3119.13,
      "sell_price": 1812.5,
      "spread_pct": 72.09,
      "est_buy_volume": 229141,
      "est_sell_volume": 154626,
      "buy_moving_week": 320797,
      "sell_moving_week": 216476
    },
    {
      "id": "BOB_OMB",
      "name": "Bob Omb",
      "buy_price": 1436.11,
      "sell_price": 847.01,
      "spread_pct": 69.55,
      "est_buy_volume": 366133,
      "est_sell_volume": 832171,
      "buy_moving_week": 512586,
      "sell_moving_week": 1165039
    },
    {
      "id": "FLAWED_AMBER_GEM",
      "name": "Flawed Amber Gem",
      "buy_price": 487.88,
      "sell_price": 290.13,
      "spread_pct": 68.16,
      "est_buy_volume": 349814,
      "est_sell_volume": 20535728,
      "buy_moving_week": 489740,
      "sell_moving_week": 28750019
    },
    {
      "id": "SHARD_SALMON",
      "name": "Shard Salmon",
      "buy_price": 5004.54,
      "sell_price": 3030.76,
      "spread_pct": 65.12,
      "est_buy_volume": 432224,
      "est_sell_volume": 735828,
      "buy_moving_week": 605114,
      "sell_moving_week": 1030159
    },
    {
      "id": "FIG_LOG",
      "name": "Fig Log",
      "buy_price": 6.9,
      "sell_price": 4.2,
      "spread_pct": 64.24,
      "est_buy_volume": 1671704,
      "est_sell_volume": 389306861,
      "buy_moving_week": 2340385,
      "sell_moving_week": 545029606
    },
    {
      "id": "FISH_BAIT",
      "name": "Fish Bait",
      "buy_price": 498.91,
      "sell_price": 307.18,
      "spread_pct": 62.42,
      "est_buy_volume": 6351930,
      "est_sell_volume": 4468382,
      "buy_moving_week": 8892702,
      "sell_moving_week": 6255735
    },
    {
      "id": "MAGMA_FISH",
      "name": "Magma Fish",
      "buy_price": 114.71,
      "sell_price": 70.85,
      "spread_pct": 61.89,
      "est_buy_volume": 557306,
      "est_sell_volume": 33131084,
      "buy_moving_week": 780229,
      "sell_moving_week": 46383517
    },
    {
      "id": "SHARD_CINDER_BAT",
      "name": "Shard Cinder Bat",
      "buy_price": 73796.8,
      "sell_price": 45787.26,
      "spread_pct": 61.17,
      "est_buy_volume": 121741,
      "est_sell_volume": 160711,
      "buy_moving_week": 170437,
      "sell_moving_week": 224996
    },
    {
      "id": "GLOWING_MUSHROOM",
      "name": "Glowing Mushroom",
      "buy_price": 1978.08,
      "sell_price": 1227.51,
      "spread_pct": 61.15,
      "est_buy_volume": 305015,
      "est_sell_volume": 579870,
      "buy_moving_week": 427021,
      "sell_moving_week": 811818
    },
    {
      "id": "ABSOLUTE_ENDER_PEARL",
      "name": "Absolute Ender Pearl",
      "buy_price": 20231.17,
      "sell_price": 12721.53,
      "spread_pct": 59.03,
      "est_buy_volume": 210059,
      "est_sell_volume": 400084,
      "buy_moving_week": 294082,
      "sell_moving_week": 560117
    },
    {
      "id": "PUMPKIN_BOMB",
      "name": "Pumpkin Bomb",
      "buy_price": 6083.46,
      "sell_price": 3847.7,
      "spread_pct": 58.11,
      "est_buy_volume": 142922,
      "est_sell_volume": 152088,
      "buy_moving_week": 200091,
      "sell_moving_week": 212923
    },
    {
      "id": "TUNGSTEN",
      "name": "Tungsten",
      "buy_price": 116.72,
      "sell_price": 74.37,
      "spread_pct": 56.93,
      "est_buy_volume": 169280,
      "est_sell_volume": 132279356,
      "buy_moving_week": 236992,
      "sell_moving_week": 185191099
    },
    {
      "id": "LUSH_BERBERIS",
      "name": "Lush Berberis",
      "buy_price": 80.0,
      "sell_price": 51.05,
      "spread_pct": 56.69,
      "est_buy_volume": 550777,
      "est_sell_volume": 1100738,
      "buy_moving_week": 771088,
      "sell_moving_week": 1541033
    },
    {
      "id": "CRUDE_GABAGOOL",
      "name": "Crude Gabagool",
      "buy_price": 599.86,
      "sell_price": 382.99,
      "spread_pct": 56.63,
      "est_buy_volume": 302767,
      "est_sell_volume": 7617583,
      "buy_moving_week": 423874,
      "sell_moving_week": 10664616
    },
    {
      "id": "HALF_EATEN_MUSHROOM",
      "name": "Half Eaten Mushroom",
      "buy_price": 698.35,
      "sell_price": 450.0,
      "spread_pct": 55.19,
      "est_buy_volume": 570545,
      "est_sell_volume": 911990,
      "buy_moving_week": 798763,
      "sell_moving_week": 1276786
    },
    {
      "id": "SLIME_BALL",
      "name": "Slime Ball",
      "buy_price": 77.39,
      "sell_price": 50.15,
      "spread_pct": 54.32,
      "est_buy_volume": 27395784,
      "est_sell_volume": 33996917,
      "buy_moving_week": 38354098,
      "sell_moving_week": 47595684
    },
    {
      "id": "JELLY",
      "name": "Jelly",
      "buy_price": 3470.25,
      "sell_price": 2264.0,
      "spread_pct": 53.28,
      "est_buy_volume": 479124,
      "est_sell_volume": 587044,
      "buy_moving_week": 670774,
      "sell_moving_week": 821862
    },
    {
      "id": "TENDER_WOOD",
      "name": "Tender Wood",
      "buy_price": 275.7,
      "sell_price": 180.2,
      "spread_pct": 53.0,
      "est_buy_volume": 1421204,
      "est_sell_volume": 14197064,
      "buy_moving_week": 1989685,
      "sell_moving_week": 19875889
    },
    {
      "id": "SHARD_LOTUS_FISH",
      "name": "Shard Lotus Fish",
      "buy_price": 4415.14,
      "sell_price": 2900.9,
      "spread_pct": 52.2,
      "est_buy_volume": 152646,
      "est_sell_volume": 122189,
      "buy_moving_week": 213705,
      "sell_moving_week": 171065
    },
    {
      "id": "ENCHANTED_GHAST_TEAR",
      "name": "Enchanted Ghast Tear",
      "buy_price": 374.09,
      "sell_price": 246.3,
      "spread_pct": 51.89,
      "est_buy_volume": 562675,
      "est_sell_volume": 3412834,
      "buy_moving_week": 787745,
      "sell_moving_week": 4777967
    },
    {
      "id": "ENCHANTED_TITANIUM",
      "name": "Enchanted Titanium",
      "buy_price": 39594.5,
      "sell_price": 27084.81,
      "spread_pct": 46.19,
      "est_buy_volume": 1154914,
      "est_sell_volume": 1091204,
      "buy_moving_week": 1616879,
      "sell_moving_week": 1527685
    },
    {
      "id": "ENCHANTED_ENDSTONE",
      "name": "Enchanted Endstone",
      "buy_price": 311.78,
      "sell_price": 215.2,
      "spread_pct": 44.88,
      "est_buy_volume": 1017193,
      "est_sell_volume": 2958005,
      "buy_moving_week": 1424070,
      "sell_moving_week": 4141207
    },
    {
      "id": "ICE_HUNK",
      "name": "Ice Hunk",
      "buy_price": 2287.7,
      "sell_price": 1580.03,
      "spread_pct": 44.79,
      "est_buy_volume": 179434,
      "est_sell_volume": 708043,
      "buy_moving_week": 251208,
      "sell_moving_week": 991260
    },
    {
      "id": "ENCHANTED_FEATHER",
      "name": "Enchanted Feather",
      "buy_price": 511.24,
      "sell_price": 354.88,
      "spread_pct": 44.06,
      "est_buy_volume": 477012,
      "est_sell_volume": 3485469,
      "buy_moving_week": 667817,
      "sell_moving_week": 4879656
    },
    {
      "id": "TREASURE_BAIT",
      "name": "Treasure Bait",
      "buy_price": 2363.78,
      "sell_price": 1646.43,
      "spread_pct": 43.57,
      "est_buy_volume": 1566755,
      "est_sell_volume": 515259,
      "buy_moving_week": 2193457,
      "sell_moving_week": 721363
    },
    {
      "id": "ENCHANTED_SAND",
      "name": "Enchanted Sand",
      "buy_price": 761.69,
      "sell_price": 531.18,
      "spread_pct": 43.4,
      "est_buy_volume": 1346071,
      "est_sell_volume": 1580834,
      "buy_moving_week": 1884500,
      "sell_moving_week": 2213167
    },
    {
      "id": "ORB_OF_ENERGY",
      "name": "Orb Of Energy",
      "buy_price": 9282.77,
      "sell_price": 6518.0,
      "spread_pct": 42.42,
      "est_buy_volume": 229361,
      "est_sell_volume": 312350,
      "buy_moving_week": 321106,
      "sell_moving_week": 437290
    },
    {
      "id": "BURNING_EYE",
      "name": "Burning Eye",
      "buy_price": 1236.41,
      "sell_price": 877.02,
      "spread_pct": 40.98,
      "est_buy_volume": 91124,
      "est_sell_volume": 1104511,
      "buy_moving_week": 127574,
      "sell_moving_week": 1546315
    },
    {
      "id": "FINE_FLOUR",
      "name": "Fine Flour",
      "buy_price": 5577.0,
      "sell_price": 3966.6,
      "spread_pct": 40.6,
      "est_buy_volume": 383493,
      "est_sell_volume": 363445,
      "buy_moving_week": 536890,
      "sell_moving_week": 508823
    },
    {
      "id": "SILVER_FANG",
      "name": "Silver Fang",
      "buy_price": 10265.9,
      "sell_price": 7302.3,
      "spread_pct": 40.58,
      "est_buy_volume": 415925,
      "est_sell_volume": 91756,
      "buy_moving_week": 582295,
      "sell_moving_week": 128458
    },
    {
      "id": "CORRUPTED_NETHER_STAR",
      "name": "Corrupted Nether Star",
      "buy_price": 14040.34,
      "sell_price": 10000.39,
      "spread_pct": 40.4,
      "est_buy_volume": 251819,
      "est_sell_volume": 255941,
      "buy_moving_week": 352547,
      "sell_moving_week": 358318
    },
    {
      "id": "OIL_BARREL",
      "name": "Oil Barrel",
      "buy_price": 2308.84,
      "sell_price": 1659.15,
      "spread_pct": 39.16,
      "est_buy_volume": 400887,
      "est_sell_volume": 583438,
      "buy_moving_week": 561242,
      "sell_moving_week": 816813
    },
    {
      "id": "SHARD_VERDANT",
      "name": "Shard Verdant",
      "buy_price": 3284.7,
      "sell_price": 2367.06,
      "spread_pct": 38.77,
      "est_buy_volume": 637036,
      "est_sell_volume": 833301,
      "buy_moving_week": 891851,
      "sell_moving_week": 1166622
    },
    {
      "id": "WOLF_TOOTH",
      "name": "Wolf Tooth",
      "buy_price": 1219.74,
      "sell_price": 884.16,
      "spread_pct": 37.95,
      "est_buy_volume": 1018816,
      "est_sell_volume": 15084330,
      "buy_moving_week": 1426342,
      "sell_moving_week": 21118062
    },
    {
      "id": "DIAMOND",
      "name": "Diamond",
      "buy_price": 7.75,
      "sell_price": 5.65,
      "spread_pct": 37.27,
      "est_buy_volume": 3380760,
      "est_sell_volume": 91452769,
      "buy_moving_week": 4733064,
      "sell_moving_week": 128033877
    },
    {
      "id": "SHARD_AZURE",
      "name": "Shard Azure",
      "buy_price": 2999.63,
      "sell_price": 2193.21,
      "spread_pct": 36.77,
      "est_buy_volume": 316524,
      "est_sell_volume": 437398,
      "buy_moving_week": 443134,
      "sell_moving_week": 612357
    },
    {
      "id": "ENCHANTED_MAGMA_CREAM",
      "name": "Enchanted Magma Cream",
      "buy_price": 2477.39,
      "sell_price": 1832.66,
      "spread_pct": 35.18,
      "est_buy_volume": 1040795,
      "est_sell_volume": 1419034,
      "buy_moving_week": 1457113,
      "sell_moving_week": 1986648
    },
    {
      "id": "WARTY",
      "name": "Warty",
      "buy_price": 12143.58,
      "sell_price": 8984.9,
      "spread_pct": 35.16,
      "est_buy_volume": 97029,
      "est_sell_volume": 99231,
      "buy_moving_week": 135841,
      "sell_moving_week": 138923
    },
    {
      "id": "RED_MUSHROOM",
      "name": "Red Mushroom",
      "buy_price": 10.9,
      "sell_price": 8.13,
      "spread_pct": 34.01,
      "est_buy_volume": 2689188,
      "est_sell_volume": 313218387,
      "buy_moving_week": 3764863,
      "sell_moving_week": 438505742
    },
    {
      "id": "ENCHANTED_ENDER_PEARL",
      "name": "Enchanted Ender Pearl",
      "buy_price": 272.75,
      "sell_price": 205.13,
      "spread_pct": 32.96,
      "est_buy_volume": 872812,
      "est_sell_volume": 6381093,
      "buy_moving_week": 1221937,
      "sell_moving_week": 8933530
    },
    {
      "id": "ENCHANTED_RAW_CHICKEN",
      "name": "Enchanted Raw Chicken",
      "buy_price": 795.72,
      "sell_price": 598.49,
      "spread_pct": 32.95,
      "est_buy_volume": 1943090,
      "est_sell_volume": 3729020,
      "buy_moving_week": 2720326,
      "sell_moving_week": 5220628
    },
    {
      "id": "ENCHANTED_GUNPOWDER",
      "name": "Enchanted Gunpowder",
      "buy_price": 1252.05,
      "sell_price": 944.07,
      "spread_pct": 32.62,
      "est_buy_volume": 849209,
      "est_sell_volume": 1047484,
      "buy_moving_week": 1188892,
      "sell_moving_week": 1466478
    },
    {
      "id": "ENCHANTED_RABBIT_HIDE",
      "name": "Enchanted Rabbit Hide",
      "buy_price": 960.48,
      "sell_price": 724.8,
      "spread_pct": 32.52,
      "est_buy_volume": 331952,
      "est_sell_volume": 2144799,
      "buy_moving_week": 464733,
      "sell_moving_week": 3002719
    },
    {
      "id": "VINESAP",
      "name": "Vinesap",
      "buy_price": 2407.36,
      "sell_price": 1824.92,
      "spread_pct": 31.92,
      "est_buy_volume": 501984,
      "est_sell_volume": 2946187,
      "buy_moving_week": 702777,
      "sell_moving_week": 4124662
    },
    {
      "id": "ENCHANTED_RAW_BEEF",
      "name": "Enchanted Raw Beef",
      "buy_price": 817.0,
      "sell_price": 620.28,
      "spread_pct": 31.71,
      "est_buy_volume": 1233984,
      "est_sell_volume": 2386666,
      "buy_moving_week": 1727578,
      "sell_moving_week": 3341333
    },
    {
      "id": "FLAWED_RUBY_GEM",
      "name": "Flawed Ruby Gem",
      "buy_price": 396.69,
      "sell_price": 304.28,
      "spread_pct": 30.37,
      "est_buy_volume": 256522,
      "est_sell_volume": 16039964,
      "buy_moving_week": 359131,
      "sell_moving_week": 22455950
    },
    {
      "id": "TITANIUM_ORE",
      "name": "Titanium Ore",
      "buy_price": 201.09,
      "sell_price": 154.31,
      "spread_pct": 30.31,
      "est_buy_volume": 869633,
      "est_sell_volume": 99920296,
      "buy_moving_week": 1217486,
      "sell_moving_week": 139888415
    },
    {
      "id": "ENCHANTED_EYE_OF_ENDER",
      "name": "Enchanted Eye Of Ender",
      "buy_price": 11087.18,
      "sell_price": 8509.83,
      "spread_pct": 30.29,
      "est_buy_volume": 424939,
      "est_sell_volume": 192251,
      "buy_moving_week": 594915,
      "sell_moving_week": 269152
    },
    {
      "id": "ENCHANTED_ROTTEN_FLESH",
      "name": "Enchanted Rotten Flesh",
      "buy_price": 653.1,
      "sell_price": 502.16,
      "spread_pct": 30.06,
      "est_buy_volume": 3943250,
      "est_sell_volume": 7281432,
      "buy_moving_week": 5520550,
      "sell_moving_week": 10194005
    },
    {
      "id": "ENCHANTED_RABBIT",
      "name": "Enchanted Rabbit",
      "buy_price": 1492.67,
      "sell_price": 1152.94,
      "spread_pct": 29.47,
      "est_buy_volume": 1518075,
      "est_sell_volume": 1417110,
      "buy_moving_week": 2125305,
      "sell_moving_week": 1983954
    },
    {
      "id": "AGARIMOO_TONGUE",
      "name": "Agarimoo Tongue",
      "buy_price": 12069.0,
      "sell_price": 9389.04,
      "spread_pct": 28.54,
      "est_buy_volume": 159921,
      "est_sell_volume": 253969,
      "buy_moving_week": 223889,
      "sell_moving_week": 355556
    },
    {
      "id": "ESSENCE_GOLD",
      "name": "Essence Gold",
      "buy_price": 884.88,
      "sell_price": 690.78,
      "spread_pct": 28.1,
      "est_buy_volume": 11904146,
      "est_sell_volume": 11967163,
      "buy_moving_week": 16665804,
      "sell_moving_week": 16754028
    },
    {
      "id": "SHARD_BEZAL",
      "name": "Shard Bezal",
      "buy_price": 19204.64,
      "sell_price": 15000.82,
      "spread_pct": 28.02,
      "est_buy_volume": 163159,
      "est_sell_volume": 104451,
      "buy_moving_week": 228422,
      "sell_moving_week": 146231
    },
    {
      "id": "SHARD_COD",
      "name": "Shard Cod",
      "buy_price": 3064.8,
      "sell_price": 2401.45,
      "spread_pct": 27.62,
      "est_buy_volume": 668380,
      "est_sell_volume": 1021687,
      "buy_moving_week": 935732,
      "sell_moving_week": 1430362
    },
    {
      "id": "ENCHANTED_POTATO",
      "name": "Enchanted Potato",
      "buy_price": 615.36,
      "sell_price": 482.65,
      "spread_pct": 27.5,
      "est_buy_volume": 11293829,
      "est_sell_volume": 92852203,
      "buy_moving_week": 15811361,
      "sell_moving_week": 129993084
    },
    {
      "id": "ENCHANTED_CLAY_BALL",
      "name": "Enchanted Clay Ball",
      "buy_price": 565.45,
      "sell_price": 443.77,
      "spread_pct": 27.42,
      "est_buy_volume": 1288145,
      "est_sell_volume": 4039599,
      "buy_moving_week": 1803403,
      "sell_moving_week": 5655439
    },
    {
      "id": "ENCHANTED_BLAZE_POWDER",
      "name": "Enchanted Blaze Powder",
      "buy_price": 3646.31,
      "sell_price": 2873.11,
      "spread_pct": 26.91,
      "est_buy_volume": 854266,
      "est_sell_volume": 1428021,
      "buy_moving_week": 1195972,
      "sell_moving_week": 1999229
    },
    {
      "id": "GOBLIN_EGG_GREEN",
      "name": "Goblin Egg Green",
      "buy_price": 5300.0,
      "sell_price": 4181.1,
      "spread_pct": 26.76,
      "est_buy_volume": 169036,
      "est_sell_volume": 249022,
      "buy_moving_week": 236651,
      "sell_moving_week": 348631
    },
    {
      "id": "SULPHURIC_COAL",
      "name": "Sulphuric Coal",
      "buy_price": 8653.98,
      "sell_price": 6855.22,
      "spread_pct": 26.24,
      "est_buy_volume": 426009,
      "est_sell_volume": 623521,
      "buy_moving_week": 596412,
      "sell_moving_week": 872929
    },
    {
      "id": "SHARD_LAPIS_ZOMBIE",
      "name": "Shard Lapis Zombie",
      "buy_price": 9777.45,
      "sell_price": 7752.05,
      "spread_pct": 26.13,
      "est_buy_volume": 257221,
      "est_sell_volume": 264822,
      "buy_moving_week": 360110,
      "sell_moving_week": 370751
    },
    {
      "id": "SHARD_BRUISER",
      "name": "Shard Bruiser",
      "buy_price": 11340.17,
      "sell_price": 9003.5,
      "spread_pct": 25.95,
      "est_buy_volume": 126663,
      "est_sell_volume": 162599,
      "buy_moving_week": 177328,
      "sell_moving_week": 227638
    },
    {
      "id": "ENCHANTED_MUTTON",
      "name": "Enchanted Mutton",
      "buy_price": 1368.82,
      "sell_price": 1090.63,
      "spread_pct": 25.51,
      "est_buy_volume": 2176800,
      "est_sell_volume": 2201789,
      "buy_moving_week": 3047520,
      "sell_moving_week": 3082504
    },
    {
      "id": "ENCHANTED_BONE",
      "name": "Enchanted Bone",
      "buy_price": 880.0,
      "sell_price": 703.1,
      "spread_pct": 25.16,
      "est_buy_volume": 992414,
      "est_sell_volume": 1309996,
      "buy_moving_week": 1389380,
      "sell_moving_week": 1833994
    },
    {
      "id": "REVENANT_FLESH",
      "name": "Revenant Flesh",
      "buy_price": 203.95,
      "sell_price": 163.09,
      "spread_pct": 25.06,
      "est_buy_volume": 2293740,
      "est_sell_volume": 28273606,
      "buy_moving_week": 3211236,
      "sell_moving_week": 39583048
    },
    {
      "id": "ENCHANTED_GLOWSTONE_DUST",
      "name": "Enchanted Glowstone Dust",
      "buy_price": 1658.95,
      "sell_price": 1331.48,
      "spread_pct": 24.59,
      "est_buy_volume": 776566,
      "est_sell_volume": 993964,
      "buy_moving_week": 1087193,
      "sell_moving_week": 1391550
    },
    {
      "id": "TOXIC_ARROW_POISON",
      "name": "Toxic Arrow Poison",
      "buy_price": 2865.84,
      "sell_price": 2304.0,
      "spread_pct": 24.39,
      "est_buy_volume": 2963206,
      "est_sell_volume": 3228256,
      "buy_moving_week": 4148489,
      "sell_moving_week": 4519559
    },
    {
      "id": "ENCHANTED_EGG",
      "name": "Enchanted Egg",
      "buy_price": 5824.48,
      "sell_price": 4683.6,
      "spread_pct": 24.36,
      "est_buy_volume": 308075,
      "est_sell_volume": 1602284,
      "buy_moving_week": 431305,
      "sell_moving_week": 2243197
    },
    {
      "id": "ESSENCE_DIAMOND",
      "name": "Essence Diamond",
      "buy_price": 396.53,
      "sell_price": 319.46,
      "spread_pct": 24.13,
      "est_buy_volume": 11474698,
      "est_sell_volume": 12105599,
      "buy_moving_week": 16064577,
      "sell_moving_week": 16947839
    },
    {
      "id": "SALTED_SUNFLOWER_SEEDS",
      "name": "Salted Sunflower Seeds",
      "buy_price": 948302.18,
      "sell_price": 765574.74,
      "spread_pct": 23.87,
      "est_buy_volume": 98742,
      "est_sell_volume": 92803,
      "buy_moving_week": 138239,
      "sell_moving_week": 129924
    },
    {
      "id": "ENCHANTED_HARD_STONE",
      "name": "Enchanted Hard Stone",
      "buy_price": 656.06,
      "sell_price": 529.78,
      "spread_pct": 23.84,
      "est_buy_volume": 1703330,
      "est_sell_volume": 26133409,
      "buy_moving_week": 2384662,
      "sell_moving_week": 36586773
    },
    {
      "id": "ENCHANTED_DARK_OAK_LOG",
      "name": "Enchanted Dark Oak Log",
      "buy_price": 2798.11,
      "sell_price": 2262.68,
      "spread_pct": 23.66,
      "est_buy_volume": 1677052,
      "est_sell_volume": 1792103,
      "buy_moving_week": 2347873,
      "sell_moving_week": 2508944
    },
    {
      "id": "ESSENCE_ICE",
      "name": "Essence Ice",
      "buy_price": 1428.88,
      "sell_price": 1158.25,
      "spread_pct": 23.36,
      "est_buy_volume": 7623890,
      "est_sell_volume": 8538286,
      "buy_moving_week": 10673446,
      "sell_moving_week": 11953601
    },
    {
      "id": "ENCHANTED_RED_SAND",
      "name": "Enchanted Red Sand",
      "buy_price": 1535.49,
      "sell_price": 1245.02,
      "spread_pct": 23.33,
      "est_buy_volume": 2742756,
      "est_sell_volume": 4510358,
      "buy_moving_week": 3839858,
      "sell_moving_week": 6314501
    },
    {
      "id": "CRUDE_GABAGOOL_DISTILLATE",
      "name": "Crude Gabagool Distillate",
      "buy_price": 13500.0,
      "sell_price": 10952.4,
      "spread_pct": 23.26,
      "est_buy_volume": 248423,
      "est_sell_volume": 495971,
      "buy_moving_week": 347792,
      "sell_moving_week": 694360
    },
    {
      "id": "ENCHANTED_ACACIA_LOG",
      "name": "Enchanted Acacia Log",
      "buy_price": 2132.34,
      "sell_price": 1731.99,
      "spread_pct": 23.12,
      "est_buy_volume": 1142790,
      "est_sell_volume": 1963764,
      "buy_moving_week": 1599906,
      "sell_moving_week": 2749269
    },
    {
      "id": "PLANT_MATTER",
      "name": "Plant Matter",
      "buy_price": 23523.24,
      "sell_price": 19131.64,
      "spread_pct": 22.95,
      "est_buy_volume": 569223,
      "est_sell_volume": 576384,
      "buy_moving_week": 796912,
      "sell_moving_week": 806938
    },
    {
      "id": "ENCHANTED_COBBLESTONE",
      "name": "Enchanted Cobblestone",
      "buy_price": 559.23,
      "sell_price": 455.94,
      "spread_pct": 22.66,
      "est_buy_volume": 3106715,
      "est_sell_volume": 7530780,
      "buy_moving_week": 4349401,
      "sell_moving_week": 10543092
    },
    {
      "id": "ENCHANTED_QUARTZ",
      "name": "Enchanted Quartz",
      "buy_price": 1599.86,
      "sell_price": 1305.81,
      "spread_pct": 22.52,
      "est_buy_volume": 627109,
      "est_sell_volume": 3025155,
      "buy_moving_week": 877952,
      "sell_moving_week": 4235217
    },
    {
      "id": "PRISMARINE_CRYSTALS",
      "name": "Prismarine Crystals",
      "buy_price": 1099.41,
      "sell_price": 899.05,
      "spread_pct": 22.29,
      "est_buy_volume": 702220,
      "est_sell_volume": 7873653,
      "buy_moving_week": 983108,
      "sell_moving_week": 11023114
    },
    {
      "id": "SHARD_FLARE",
      "name": "Shard Flare",
      "buy_price": 26883.96,
      "sell_price": 22001.47,
      "spread_pct": 22.19,
      "est_buy_volume": 106111,
      "est_sell_volume": 155360,
      "buy_moving_week": 148556,
      "sell_moving_week": 217504
    },
    {
      "id": "IRON_INGOT",
      "name": "Iron Ingot",
      "buy_price": 4.14,
      "sell_price": 3.4,
      "spread_pct": 21.62,
      "est_buy_volume": 6548936,
      "est_sell_volume": 161591363,
      "buy_moving_week": 9168511,
      "sell_moving_week": 226227908
    },
    {
      "id": "LOTUS_SILVER",
      "name": "Lotus Silver",
      "buy_price": 16080.0,
      "sell_price": 13247.59,
      "spread_pct": 21.38,
      "est_buy_volume": 145560,
      "est_sell_volume": 563788,
      "buy_moving_week": 203784,
      "sell_moving_week": 789303
    },
    {
      "id": "KUUDRA_TEETH",
      "name": "Kuudra Teeth",
      "buy_price": 8459.14,
      "sell_price": 7000.0,
      "spread_pct": 20.84,
      "est_buy_volume": 244194,
      "est_sell_volume": 408476,
      "buy_moving_week": 341872,
      "sell_moving_week": 571866
    },
    {
      "id": "SHARD_GHOST",
      "name": "Shard Ghost",
      "buy_price": 14714.5,
      "sell_price": 12209.16,
      "spread_pct": 20.52,
      "est_buy_volume": 544823,
      "est_sell_volume": 464438,
      "buy_moving_week": 762752,
      "sell_moving_week": 650213
    }
  ],
  "products_scanned": 1939,
  "last_updated": "2026-07-23T09:59:13.366696+00:00",
  "error": null,
  "last_checked": "2026-07-23T09:59:13.366718+00:00",
  "config": {
    "volume_threshold": 90000.0,
    "spread_threshold_pct": 20.0,
    "window_days": 5.0,
    "poll_interval_minutes": 30
  }
}